global_logger/__init__.py
global_logger/global_logger.py
global_logger/requirements.txt
global_logger-0.4.7.dist-info/AUTHORS.rst
global_logger-0.4.7.dist-info/LICENSE
global_logger-0.4.7.dist-info/METADATA
global_logger-0.4.7.dist-info/WHEEL
global_logger-0.4.7.dist-info/RECORD
